simple_rpc/.gitignore
simple_rpc/__init__.py
simple_rpc/client/__init__.py
simple_rpc/server/__init__.py
caffeinism_simple_rpc-0.0.1.dist-info/METADATA
caffeinism_simple_rpc-0.0.1.dist-info/WHEEL
caffeinism_simple_rpc-0.0.1.dist-info/RECORD
